pyseqrna/__init__.py
pyseqrna/__main__.py
pyseqrna/aligners.py
pyseqrna/arg_parser.py
pyseqrna/clustering.py
pyseqrna/differential_expression.py
pyseqrna/gene_ontology.py
pyseqrna/multimapped_groups.py
pyseqrna/normalize_counts.py
pyseqrna/pathway.py
pyseqrna/pyseqrna_plots.py
pyseqrna/pyseqrna_stats.py
pyseqrna/pyseqrna_utils.py
pyseqrna/quality_check.py
pyseqrna/quality_trimming.py
pyseqrna/quantification.py
pyseqrna/report.py
pyseqrna/ribosomal.py
pyseqrna/version.py
pyseqrna/param/STAR.ini
pyseqrna/param/bowtie2.ini
pyseqrna/param/fastqc.ini
pyseqrna/param/featureCount.ini
pyseqrna/param/flexbar.ini
pyseqrna/param/hisat2.ini
pyseqrna/param/htseq.ini
pyseqrna/param/trim_galore.ini
pyseqrna/param/trimmomaticPE.ini
pyseqrna/param/trimmomaticSE.ini
pySeqRNA-0.0.2.dist-info/LICENSE
pySeqRNA-0.0.2.dist-info/METADATA
pySeqRNA-0.0.2.dist-info/WHEEL
pySeqRNA-0.0.2.dist-info/entry_points.txt
pySeqRNA-0.0.2.dist-info/top_level.txt
pySeqRNA-0.0.2.dist-info/RECORD
